syncverse/__init__.py
syncverse/gdrive_sync.py
syncverse/local_sync.py
syncverse-0.1.3.dist-info/METADATA
syncverse-0.1.3.dist-info/WHEEL
syncverse-0.1.3.dist-info/top_level.txt
syncverse-0.1.3.dist-info/RECORD
